{
    "48": {
        "title": "Product details",
        "slug": "product-details",
        "original_file": "index.html?p=48.html",
        "file_path": "\/Users\/martin\/23point4\/Chambers-Inc\/mirror\/index.html?p=48.html"
    },
    "24": {
        "title": "Contact Chambers Inc",
        "slug": "contact-chambers-inc",
        "original_file": "index.html?p=24.html",
        "file_path": "\/Users\/martin\/23point4\/Chambers-Inc\/mirror\/index.html?p=24.html"
    },
    "22": {
        "title": "About Us",
        "slug": "about-us",
        "original_file": "index.html?p=22.html",
        "file_path": "\/Users\/martin\/23point4\/Chambers-Inc\/mirror\/index.html?p=22.html"
    },
    "125": {
        "title": "Mobile PC Rescue Test",
        "slug": "mobile-pc-rescue-test",
        "original_file": "index.html?p=125.html",
        "file_path": "\/Users\/martin\/23point4\/Chambers-Inc\/mirror\/index.html?p=125.html"
    },
    "144": {
        "title": "New Development in High Speed Printing",
        "slug": "new-development-in-high-speed-printing",
        "original_file": "index.html?p=144.html",
        "file_path": "\/Users\/martin\/23point4\/Chambers-Inc\/mirror\/index.html?p=144.html"
    }
}